{
	"parent": "block/cube",
	"display": {
		"firstperson_righthand": {
			"rotation":    [ 0,   135,   0   ],
			"translation": [ 0,     0,   0   ],
			"scale":       [ 0.4,   0.4, 0.4 ]
		}
	},
	"textures": {
		"up":       "bigtech:block/destroyer_top",
		"down":     "bigtech:block/destroyer_top",
		"north":    "bigtech:block/short_range_deployer_front",
		"east":     "bigtech:block/destroyer_side",
		"south":    "bigtech:block/destroyer_side",
		"west":     "bigtech:block/destroyer_side",
		"particle": "bigtech:block/short_range_deployer_front"
	}
}